{
  "date": "2026-07-22",
  "generated_at": "2026-07-23T22:54:40.982514+00:00",
  "methodology_version": "1.0",
  "parameters": {
    "srisk_k": 0.08,
    "covar_quantile": 0.05,
    "covar_window_days": 252,
    "lrmes_horizon_days": 22,
    "lrmes_market_drop": 0.4,
    "mes_tail_pct": 0.05
  },
  "system_srisk_usd_bn": 3193.2256,
  "bank_count": 28,
  "banks": [
    {
      "bank_name": "Agricultural Bank of China",
      "region": "CN",
      "covar_index": "^HSI",
      "mes": -0.011614,
      "lrmes": 0.238076,
      "covar": -0.022911,
      "delta_covar": -0.006435,
      "covar_beta": 0.229654,
      "srisk_usd_bn": 454.302778,
      "market_cap_usd_bn": 156.976614,
      "debt_usd_bn": 7054.233854,
      "srisk_share_pct": 14.2271,
      "bank_id": "ABC"
    },
    {
      "bank_name": "Crédit Agricole",
      "region": "EU",
      "covar_index": "^STOXX50E",
      "mes": -0.017979,
      "lrmes": 0.373982,
      "covar": -0.02435,
      "delta_covar": -0.013718,
      "covar_beta": 0.56046,
      "srisk_usd_bn": 176.203722,
      "market_cap_usd_bn": 62.931744,
      "debt_usd_bn": 2655.604907,
      "srisk_share_pct": 5.518,
      "bank_id": "ACA"
    },
    {
      "bank_name": "Bank of America",
      "region": "US",
      "covar_index": "^GSPC",
      "mes": -0.014999,
      "lrmes": 0.345195,
      "covar": -0.020162,
      "delta_covar": -0.009277,
      "covar_beta": 0.366555,
      "srisk_usd_bn": 0.0,
      "market_cap_usd_bn": 432.447147,
      "debt_usd_bn": 3195.518,
      "srisk_share_pct": 0.0,
      "bank_id": "BAC"
    },
    {
      "bank_name": "Barclays",
      "region": "GB",
      "covar_index": "^FTSE",
      "mes": -0.026539,
      "lrmes": 0.602628,
      "covar": -0.019228,
      "delta_covar": -0.011649,
      "covar_beta": 0.339565,
      "srisk_usd_bn": 77.306327,
      "market_cap_usd_bn": 53.123567,
      "debt_usd_bn": 1209.092141,
      "srisk_share_pct": 2.4209,
      "bank_id": "BARC"
    },
    {
      "bank_name": "BBVA",
      "region": "EU",
      "covar_index": "^STOXX50E",
      "mes": -0.020178,
      "lrmes": 0.474782,
      "covar": -0.018152,
      "delta_covar": -0.00648,
      "covar_beta": 0.23762,
      "srisk_usd_bn": 6.126782,
      "market_cap_usd_bn": 144.681986,
      "debt_usd_bn": 950.465252,
      "srisk_share_pct": 0.1919,
      "bank_id": "BBVA"
    },
    {
      "bank_name": "BNP Paribas",
      "region": "EU",
      "covar_index": "^STOXX50E",
      "mes": -0.021602,
      "lrmes": 0.449227,
      "covar": -0.02219,
      "delta_covar": -0.011372,
      "covar_beta": 0.364526,
      "srisk_usd_bn": 186.998752,
      "market_cap_usd_bn": 134.141759,
      "debt_usd_bn": 3187.122741,
      "srisk_share_pct": 5.8561,
      "bank_id": "BNP"
    },
    {
      "bank_name": "Bank of China",
      "region": "CN",
      "covar_index": "^HSI",
      "mes": -0.009442,
      "lrmes": 0.248848,
      "covar": -0.024246,
      "delta_covar": -0.007977,
      "covar_beta": 0.410143,
      "srisk_usd_bn": 339.161024,
      "market_cap_usd_bn": 131.129855,
      "debt_usd_bn": 5372.245238,
      "srisk_share_pct": 10.6213,
      "bank_id": "BOC"
    },
    {
      "bank_name": "Bank of Communications",
      "region": "CN",
      "covar_index": "^HSI",
      "mes": -0.010143,
      "lrmes": 0.220372,
      "covar": -0.025083,
      "delta_covar": -0.008543,
      "covar_beta": 0.446258,
      "srisk_usd_bn": 141.294076,
      "market_cap_usd_bn": 49.819017,
      "debt_usd_bn": 2212.839648,
      "srisk_share_pct": 4.4248,
      "bank_id": "BOCOM"
    },
    {
      "bank_name": "Groupe BPCE",
      "region": "EU",
      "covar_index": "^STOXX50E",
      "mes": -0.032804,
      "lrmes": 0.574532,
      "covar": -0.019332,
      "delta_covar": -0.008199,
      "covar_beta": 0.210609,
      "srisk_usd_bn": 115.658653,
      "market_cap_usd_bn": 64.986348,
      "debt_usd_bn": 1763.703914,
      "srisk_share_pct": 3.622,
      "bank_id": "BPCE"
    },
    {
      "bank_name": "Citigroup",
      "region": "US",
      "covar_index": "^GSPC",
      "mes": -0.024722,
      "lrmes": 0.502362,
      "covar": -0.018813,
      "delta_covar": -0.008857,
      "covar_beta": 0.306343,
      "srisk_usd_bn": 103.646694,
      "market_cap_usd_bn": 221.83615,
      "debt_usd_bn": 2565.115,
      "srisk_share_pct": 3.2458,
      "bank_id": "C"
    },
    {
      "bank_name": "China Construction Bank",
      "region": "CN",
      "covar_index": "^HSI",
      "mes": -0.012739,
      "lrmes": 0.272625,
      "covar": -0.021928,
      "delta_covar": -0.005366,
      "covar_beta": 0.251628,
      "srisk_usd_bn": 395.377861,
      "market_cap_usd_bn": 175.386617,
      "debt_usd_bn": 6409.299083,
      "srisk_share_pct": 12.3818,
      "bank_id": "CCB"
    },
    {
      "bank_name": "Deutsche Bank",
      "region": "EU",
      "covar_index": "^STOXX50E",
      "mes": -0.022971,
      "lrmes": 0.522741,
      "covar": -0.023137,
      "delta_covar": -0.013201,
      "covar_beta": 0.39234,
      "srisk_usd_bn": 98.118969,
      "market_cap_usd_bn": 68.124682,
      "debt_usd_bn": 1600.38769,
      "srisk_share_pct": 3.0727,
      "bank_id": "DBK"
    },
    {
      "bank_name": "Société Générale",
      "region": "EU",
      "covar_index": "^STOXX50E",
      "mes": -0.032804,
      "lrmes": 0.574532,
      "covar": -0.019332,
      "delta_covar": -0.008199,
      "covar_beta": 0.210609,
      "srisk_usd_bn": 115.658653,
      "market_cap_usd_bn": 64.986348,
      "debt_usd_bn": 1763.703914,
      "srisk_share_pct": 3.622,
      "bank_id": "GLE"
    },
    {
      "bank_name": "Goldman Sachs",
      "region": "US",
      "covar_index": "^GSPC",
      "mes": -0.026014,
      "lrmes": 0.548579,
      "covar": -0.018596,
      "delta_covar": -0.008419,
      "covar_beta": 0.294654,
      "srisk_usd_bn": 20.441775,
      "market_cap_usd_bn": 323.977135,
      "debt_usd_bn": 1937.398,
      "srisk_share_pct": 0.6402,
      "bank_id": "GS"
    },
    {
      "bank_name": "HSBC Holdings",
      "region": "GB",
      "covar_index": "^FTSE",
      "mes": -0.027805,
      "lrmes": 0.586084,
      "covar": -0.018016,
      "delta_covar": -0.008678,
      "covar_beta": 0.328209,
      "srisk_usd_bn": 110.672515,
      "market_cap_usd_bn": 197.511306,
      "debt_usd_bn": 2323.566368,
      "srisk_share_pct": 3.4659,
      "bank_id": "HSBC"
    },
    {
      "bank_name": "Industrial & Commercial Bank of China",
      "region": "CN",
      "covar_index": "^HSI",
      "mes": -0.01051,
      "lrmes": 0.240912,
      "covar": -0.025035,
      "delta_covar": -0.008472,
      "covar_beta": 0.376342,
      "srisk_usd_bn": 471.359053,
      "market_cap_usd_bn": 195.629936,
      "debt_usd_bn": 7599.743008,
      "srisk_share_pct": 14.7612,
      "bank_id": "ICBC"
    },
    {
      "bank_name": "ING Groep",
      "region": "EU",
      "covar_index": "^STOXX50E",
      "mes": -0.019376,
      "lrmes": 0.431286,
      "covar": -0.020489,
      "delta_covar": -0.010724,
      "covar_beta": 0.437688,
      "srisk_usd_bn": 49.216017,
      "market_cap_usd_bn": 95.199258,
      "debt_usd_bn": 1237.822983,
      "srisk_share_pct": 1.5413,
      "bank_id": "ING"
    },
    {
      "bank_name": "JPMorgan Chase",
      "region": "US",
      "covar_index": "^GSPC",
      "mes": -0.016262,
      "lrmes": 0.368122,
      "covar": -0.017205,
      "delta_covar": -0.005067,
      "covar_beta": 0.20383,
      "srisk_usd_bn": 0.0,
      "market_cap_usd_bn": 925.611799,
      "debt_usd_bn": 4536.437,
      "srisk_share_pct": 0.0,
      "bank_id": "JPM"
    },
    {
      "bank_name": "Mizuho Financial Group",
      "region": "JP",
      "covar_index": "^N225",
      "mes": -0.03487,
      "lrmes": 0.391956,
      "covar": -0.03619,
      "delta_covar": -0.015446,
      "covar_beta": 0.358533,
      "srisk_usd_bn": 71.34394,
      "market_cap_usd_bn": 127.341705,
      "debt_usd_bn": 1782.23706,
      "srisk_share_pct": 2.2342,
      "bank_id": "MFG"
    },
    {
      "bank_name": "Morgan Stanley",
      "region": "US",
      "covar_index": "^GSPC",
      "mes": -0.023664,
      "lrmes": 0.499912,
      "covar": -0.017624,
      "delta_covar": -0.008714,
      "covar_beta": 0.297185,
      "srisk_usd_bn": 0.0,
      "market_cap_usd_bn": 343.482,
      "debt_usd_bn": 1466.034,
      "srisk_share_pct": 0.0,
      "bank_id": "MS"
    },
    {
      "bank_name": "Mitsubishi UFJ Financial",
      "region": "JP",
      "covar_index": "^N225",
      "mes": -0.025127,
      "lrmes": 0.301277,
      "covar": -0.037961,
      "delta_covar": -0.01521,
      "covar_beta": 0.444621,
      "srisk_usd_bn": 37.070858,
      "market_cap_usd_bn": 253.474968,
      "debt_usd_bn": 2500.137119,
      "srisk_share_pct": 1.1609,
      "bank_id": "MUFG"
    },
    {
      "bank_name": "Banco Santander",
      "region": "EU",
      "covar_index": "^STOXX50E",
      "mes": -0.026424,
      "lrmes": 0.532303,
      "covar": -0.019163,
      "delta_covar": -0.010917,
      "covar_beta": 0.388727,
      "srisk_usd_bn": 74.328224,
      "market_cap_usd_bn": 197.045142,
      "debt_usd_bn": 1988.912028,
      "srisk_share_pct": 2.3277,
      "bank_id": "SAN"
    },
    {
      "bank_name": "Sumitomo Mitsui Financial",
      "region": "JP",
      "covar_index": "^N225",
      "mes": -0.028524,
      "lrmes": 0.334328,
      "covar": -0.03642,
      "delta_covar": -0.015286,
      "covar_beta": 0.450299,
      "srisk_usd_bn": 52.065639,
      "market_cap_usd_bn": 165.200864,
      "debt_usd_bn": 1915.470615,
      "srisk_share_pct": 1.6305,
      "bank_id": "SMFG"
    },
    {
      "bank_name": "Standard Chartered",
      "region": "GB",
      "covar_index": "^FTSE",
      "mes": -0.029947,
      "lrmes": 0.613268,
      "covar": -0.016462,
      "delta_covar": -0.007761,
      "covar_beta": 0.261411,
      "srisk_usd_bn": 42.442485,
      "market_cap_usd_bn": 35.026064,
      "debt_usd_bn": 686.306694,
      "srisk_share_pct": 1.3291,
      "bank_id": "STAN"
    },
    {
      "bank_name": "State Street",
      "region": "US",
      "covar_index": "^GSPC",
      "mes": -0.018449,
      "lrmes": 0.42542,
      "covar": -0.018986,
      "delta_covar": -0.007917,
      "covar_beta": 0.281321,
      "srisk_usd_bn": 2.254846,
      "market_cap_usd_bn": 50.885902,
      "debt_usd_bn": 364.423,
      "srisk_share_pct": 0.0706,
      "bank_id": "STT"
    },
    {
      "bank_name": "UBS Group",
      "region": "EU",
      "covar_index": "^STOXX50E",
      "mes": -0.013817,
      "lrmes": 0.362757,
      "covar": -0.019721,
      "delta_covar": -0.007624,
      "covar_beta": 0.339172,
      "srisk_usd_bn": 36.640572,
      "market_cap_usd_bn": 114.211302,
      "debt_usd_bn": 1294.981009,
      "srisk_share_pct": 1.1474,
      "bank_id": "UBS"
    },
    {
      "bank_name": "UniCredit",
      "region": "EU",
      "covar_index": "^STOXX50E",
      "mes": -0.021039,
      "lrmes": 0.524867,
      "covar": -0.021542,
      "delta_covar": -0.010334,
      "covar_beta": 0.362631,
      "srisk_usd_bn": 13.880605,
      "market_cap_usd_bn": 142.173174,
      "debt_usd_bn": 950.345512,
      "srisk_share_pct": 0.4347,
      "bank_id": "UCG"
    },
    {
      "bank_name": "Wells Fargo",
      "region": "US",
      "covar_index": "^GSPC",
      "mes": -0.014764,
      "lrmes": 0.340825,
      "covar": -0.018122,
      "delta_covar": -0.00722,
      "covar_beta": 0.234846,
      "srisk_usd_bn": 1.654766,
      "market_cap_usd_bn": 264.46157,
      "debt_usd_bn": 2025.439,
      "srisk_share_pct": 0.0518,
      "bank_id": "WFC"
    }
  ]
}