{
  "date": "2026-05-15",
  "generated_at": "2026-06-22T23:17:40.986367+00:00",
  "methodology_version": "1.0",
  "parameters": {
    "srisk_k": 0.08,
    "covar_quantile": 0.05,
    "covar_window_days": 252,
    "lrmes_horizon_days": 22,
    "lrmes_market_drop": 0.4,
    "mes_tail_pct": 0.05
  },
  "system_srisk_usd_bn": 527.0288,
  "bank_count": 11,
  "banks": [
    {
      "bank_name": "Bank of America",
      "region": "US",
      "covar_index": "^GSPC",
      "mes": -0.020453,
      "lrmes": 0.459179,
      "covar": -0.018006,
      "delta_covar": -0.008548,
      "covar_beta": 0.32972,
      "srisk_usd_bn": 80.814623,
      "market_cap_usd_bn": 351.371683,
      "debt_usd_bn": 3195.518,
      "srisk_share_pct": 15.334,
      "bank_id": "BAC"
    },
    {
      "bank_name": "Barclays",
      "region": "GB",
      "covar_index": "^FTSE",
      "mes": -0.024484,
      "lrmes": 0.608029,
      "covar": -0.016349,
      "delta_covar": -0.009729,
      "covar_beta": 0.286414,
      "srisk_usd_bn": 81.242338,
      "market_cap_usd_bn": 42.6968,
      "debt_usd_bn": 1207.992081,
      "srisk_share_pct": 15.4152,
      "bank_id": "BARC"
    },
    {
      "bank_name": "Bank of New York Mellon",
      "region": "US",
      "covar_index": "^GSPC",
      "mes": -0.01476,
      "lrmes": 0.358256,
      "covar": -0.01993,
      "delta_covar": -0.009711,
      "covar_beta": 0.445245,
      "srisk_usd_bn": 0.0,
      "market_cap_usd_bn": 92.674896,
      "debt_usd_bn": 516.198,
      "srisk_share_pct": 0.0,
      "bank_id": "BK"
    },
    {
      "bank_name": "Citigroup",
      "region": "US",
      "covar_index": "^GSPC",
      "mes": -0.025637,
      "lrmes": 0.537188,
      "covar": -0.017544,
      "delta_covar": -0.008436,
      "covar_beta": 0.288414,
      "srisk_usd_bn": 115.579972,
      "market_cap_usd_bn": 210.502305,
      "debt_usd_bn": 2565.115,
      "srisk_share_pct": 21.9305,
      "bank_id": "C"
    },
    {
      "bank_name": "Goldman Sachs",
      "region": "US",
      "covar_index": "^GSPC",
      "mes": -0.022089,
      "lrmes": 0.527952,
      "covar": -0.016515,
      "delta_covar": -0.007403,
      "covar_beta": 0.298919,
      "srisk_usd_bn": 34.00976,
      "market_cap_usd_bn": 278.577935,
      "debt_usd_bn": 1937.398,
      "srisk_share_pct": 6.4531,
      "bank_id": "GS"
    },
    {
      "bank_name": "HSBC Holdings",
      "region": "GB",
      "covar_index": "^FTSE",
      "mes": -0.023881,
      "lrmes": 0.560059,
      "covar": -0.01428,
      "delta_covar": -0.006872,
      "covar_beta": 0.273529,
      "srisk_usd_bn": 117.094093,
      "market_cap_usd_bn": 169.543832,
      "debt_usd_bn": 2321.452333,
      "srisk_share_pct": 22.2178,
      "bank_id": "HSBC"
    },
    {
      "bank_name": "JPMorgan Chase",
      "region": "US",
      "covar_index": "^GSPC",
      "mes": -0.018563,
      "lrmes": 0.427561,
      "covar": -0.018157,
      "delta_covar": -0.008664,
      "covar_beta": 0.353888,
      "srisk_usd_bn": 0.0,
      "market_cap_usd_bn": 797.985289,
      "debt_usd_bn": 4536.437,
      "srisk_share_pct": 0.0,
      "bank_id": "JPM"
    },
    {
      "bank_name": "Morgan Stanley",
      "region": "US",
      "covar_index": "^GSPC",
      "mes": -0.02258,
      "lrmes": 0.502082,
      "covar": -0.016249,
      "delta_covar": -0.007654,
      "covar_beta": 0.288321,
      "srisk_usd_bn": 0.0,
      "market_cap_usd_bn": 303.643091,
      "debt_usd_bn": 1466.034,
      "srisk_share_pct": 0.0,
      "bank_id": "MS"
    },
    {
      "bank_name": "Standard Chartered",
      "region": "GB",
      "covar_index": "^FTSE",
      "mes": -0.024625,
      "lrmes": 0.572958,
      "covar": -0.014446,
      "delta_covar": -0.006641,
      "covar_beta": 0.238676,
      "srisk_usd_bn": 42.791175,
      "market_cap_usd_bn": 30.705155,
      "debt_usd_bn": 685.682276,
      "srisk_share_pct": 8.1193,
      "bank_id": "STAN"
    },
    {
      "bank_name": "State Street",
      "region": "US",
      "covar_index": "^GSPC",
      "mes": -0.021918,
      "lrmes": 0.48246,
      "covar": -0.017775,
      "delta_covar": -0.009081,
      "covar_beta": 0.321381,
      "srisk_usd_bn": 9.011416,
      "market_cap_usd_bn": 42.303843,
      "debt_usd_bn": 364.423,
      "srisk_share_pct": 1.7099,
      "bank_id": "STT"
    },
    {
      "bank_name": "Wells Fargo",
      "region": "US",
      "covar_index": "^GSPC",
      "mes": -0.019353,
      "lrmes": 0.440992,
      "covar": -0.01836,
      "delta_covar": -0.009049,
      "covar_beta": 0.292118,
      "srisk_usd_bn": 46.485438,
      "market_cap_usd_bn": 224.679107,
      "debt_usd_bn": 2025.439,
      "srisk_share_pct": 8.8203,
      "bank_id": "WFC"
    }
  ]
}