{
  "date": "2026-06-23",
  "generated_at": "2026-07-03T23:01:30.212861+00:00",
  "methodology_version": "1.0",
  "parameters": {
    "srisk_k": 0.08,
    "covar_quantile": 0.05,
    "covar_window_days": 252,
    "lrmes_horizon_days": 22,
    "lrmes_market_drop": 0.4,
    "mes_tail_pct": 0.05
  },
  "system_srisk_usd_bn": 3276.586,
  "bank_count": 29,
  "banks": [
    {
      "bank_name": "Agricultural Bank of China",
      "region": "CN",
      "covar_index": "^HSI",
      "mes": -0.013641,
      "lrmes": 0.272376,
      "covar": -0.022145,
      "delta_covar": -0.007086,
      "covar_beta": 0.276502,
      "srisk_usd_bn": 458.542825,
      "market_cap_usd_bn": 156.935176,
      "debt_usd_bn": 7044.967247,
      "srisk_share_pct": 13.9945,
      "bank_id": "ABC"
    },
    {
      "bank_name": "Crédit Agricole",
      "region": "EU",
      "covar_index": "^STOXX50E",
      "mes": -0.017277,
      "lrmes": 0.378472,
      "covar": -0.024593,
      "delta_covar": -0.013961,
      "covar_beta": 0.560456,
      "srisk_usd_bn": 178.077674,
      "market_cap_usd_bn": 60.869059,
      "debt_usd_bn": 2661.037036,
      "srisk_share_pct": 5.4349,
      "bank_id": "ACA"
    },
    {
      "bank_name": "Bank of America",
      "region": "US",
      "covar_index": "^GSPC",
      "mes": -0.016456,
      "lrmes": 0.372522,
      "covar": -0.019427,
      "delta_covar": -0.009033,
      "covar_beta": 0.355417,
      "srisk_usd_bn": 18.400423,
      "market_cap_usd_bn": 410.963564,
      "debt_usd_bn": 3195.518,
      "srisk_share_pct": 0.5616,
      "bank_id": "BAC"
    },
    {
      "bank_name": "Barclays",
      "region": "GB",
      "covar_index": "^FTSE",
      "mes": -0.025202,
      "lrmes": 0.611347,
      "covar": -0.018252,
      "delta_covar": -0.010644,
      "covar_beta": 0.310261,
      "srisk_usd_bn": 79.07149,
      "market_cap_usd_bn": 52.075043,
      "debt_usd_bn": 1221.143728,
      "srisk_share_pct": 2.4132,
      "bank_id": "BARC"
    },
    {
      "bank_name": "BBVA",
      "region": "EU",
      "covar_index": "^STOXX50E",
      "mes": -0.018119,
      "lrmes": 0.483707,
      "covar": -0.018459,
      "delta_covar": -0.007307,
      "covar_beta": 0.255355,
      "srisk_usd_bn": 10.924422,
      "market_cap_usd_bn": 137.410004,
      "debt_usd_bn": 952.409461,
      "srisk_share_pct": 0.3334,
      "bank_id": "BBVA"
    },
    {
      "bank_name": "Bank of New York Mellon",
      "region": "US",
      "covar_index": "^GSPC",
      "mes": -0.015525,
      "lrmes": 0.35577,
      "covar": -0.019982,
      "delta_covar": -0.009471,
      "covar_beta": 0.41811,
      "srisk_usd_bn": 0.0,
      "market_cap_usd_bn": 101.096758,
      "debt_usd_bn": 516.198,
      "srisk_share_pct": 0.0,
      "bank_id": "BK"
    },
    {
      "bank_name": "BNP Paribas",
      "region": "EU",
      "covar_index": "^STOXX50E",
      "mes": -0.020019,
      "lrmes": 0.454643,
      "covar": -0.021916,
      "delta_covar": -0.010611,
      "covar_beta": 0.364525,
      "srisk_usd_bn": 191.423596,
      "market_cap_usd_bn": 127.694089,
      "debt_usd_bn": 3193.642108,
      "srisk_share_pct": 5.8422,
      "bank_id": "BNP"
    },
    {
      "bank_name": "Bank of China",
      "region": "CN",
      "covar_index": "^HSI",
      "mes": -0.011826,
      "lrmes": 0.249548,
      "covar": -0.024301,
      "delta_covar": -0.010614,
      "covar_beta": 0.545106,
      "srisk_usd_bn": 338.270613,
      "market_cap_usd_bn": 131.724217,
      "debt_usd_bn": 5365.188131,
      "srisk_share_pct": 10.3239,
      "bank_id": "BOC"
    },
    {
      "bank_name": "Bank of Communications",
      "region": "CN",
      "covar_index": "^HSI",
      "mes": -0.011232,
      "lrmes": 0.230359,
      "covar": -0.025344,
      "delta_covar": -0.009187,
      "covar_beta": 0.512767,
      "srisk_usd_bn": 142.02713,
      "market_cap_usd_bn": 49.101777,
      "debt_usd_bn": 2209.93281,
      "srisk_share_pct": 4.3346,
      "bank_id": "BOCOM"
    },
    {
      "bank_name": "Groupe BPCE",
      "region": "EU",
      "covar_index": "^STOXX50E",
      "mes": -0.029236,
      "lrmes": 0.538858,
      "covar": -0.019246,
      "delta_covar": -0.008061,
      "covar_beta": 0.210581,
      "srisk_usd_bn": 114.02345,
      "market_cap_usd_bn": 64.493615,
      "debt_usd_bn": 1767.31163,
      "srisk_share_pct": 3.4799,
      "bank_id": "BPCE"
    },
    {
      "bank_name": "Citigroup",
      "region": "US",
      "covar_index": "^GSPC",
      "mes": -0.023669,
      "lrmes": 0.499125,
      "covar": -0.017069,
      "delta_covar": -0.00726,
      "covar_beta": 0.269655,
      "srisk_usd_bn": 91.271746,
      "market_cap_usd_bn": 247.257493,
      "debt_usd_bn": 2565.115,
      "srisk_share_pct": 2.7856,
      "bank_id": "C"
    },
    {
      "bank_name": "China Construction Bank",
      "region": "CN",
      "covar_index": "^HSI",
      "mes": -0.013993,
      "lrmes": 0.278319,
      "covar": -0.02162,
      "delta_covar": -0.007196,
      "covar_beta": 0.344727,
      "srisk_usd_bn": 397.518866,
      "market_cap_usd_bn": 172.531181,
      "debt_usd_bn": 6400.879677,
      "srisk_share_pct": 12.1321,
      "bank_id": "CCB"
    },
    {
      "bank_name": "Deutsche Bank",
      "region": "EU",
      "covar_index": "^STOXX50E",
      "mes": -0.020349,
      "lrmes": 0.521976,
      "covar": -0.023137,
      "delta_covar": -0.01333,
      "covar_beta": 0.392338,
      "srisk_usd_bn": 98.526363,
      "market_cap_usd_bn": 67.684688,
      "debt_usd_bn": 1603.661337,
      "srisk_share_pct": 3.007,
      "bank_id": "DBK"
    },
    {
      "bank_name": "Société Générale",
      "region": "EU",
      "covar_index": "^STOXX50E",
      "mes": -0.029236,
      "lrmes": 0.538858,
      "covar": -0.019246,
      "delta_covar": -0.008061,
      "covar_beta": 0.210581,
      "srisk_usd_bn": 114.02345,
      "market_cap_usd_bn": 64.493615,
      "debt_usd_bn": 1767.31163,
      "srisk_share_pct": 3.4799,
      "bank_id": "GLE"
    },
    {
      "bank_name": "Goldman Sachs",
      "region": "US",
      "covar_index": "^GSPC",
      "mes": -0.025329,
      "lrmes": 0.542591,
      "covar": -0.017731,
      "delta_covar": -0.008255,
      "covar_beta": 0.311293,
      "srisk_usd_bn": 19.123691,
      "market_cap_usd_bn": 322.867905,
      "debt_usd_bn": 1937.398,
      "srisk_share_pct": 0.5836,
      "bank_id": "GS"
    },
    {
      "bank_name": "HSBC Holdings",
      "region": "GB",
      "covar_index": "^FTSE",
      "mes": -0.027907,
      "lrmes": 0.596381,
      "covar": -0.018016,
      "delta_covar": -0.008752,
      "covar_beta": 0.328207,
      "srisk_usd_bn": 118.241415,
      "market_cap_usd_bn": 187.156511,
      "debt_usd_bn": 2346.726441,
      "srisk_share_pct": 3.6087,
      "bank_id": "HSBC"
    },
    {
      "bank_name": "Industrial & Commercial Bank of China",
      "region": "CN",
      "covar_index": "^HSI",
      "mes": -0.010896,
      "lrmes": 0.243756,
      "covar": -0.024653,
      "delta_covar": -0.009359,
      "covar_beta": 0.438623,
      "srisk_usd_bn": 471.885849,
      "market_cap_usd_bn": 194.460705,
      "debt_usd_bn": 7589.759808,
      "srisk_share_pct": 14.4018,
      "bank_id": "ICBC"
    },
    {
      "bank_name": "ING Groep",
      "region": "EU",
      "covar_index": "^STOXX50E",
      "mes": -0.018341,
      "lrmes": 0.436751,
      "covar": -0.020595,
      "delta_covar": -0.010899,
      "covar_beta": 0.437638,
      "srisk_usd_bn": 51.944615,
      "market_cap_usd_bn": 91.248068,
      "debt_usd_bn": 1240.354991,
      "srisk_share_pct": 1.5853,
      "bank_id": "ING"
    },
    {
      "bank_name": "JPMorgan Chase",
      "region": "US",
      "covar_index": "^GSPC",
      "mes": -0.016649,
      "lrmes": 0.37595,
      "covar": -0.017502,
      "delta_covar": -0.006138,
      "covar_beta": 0.243757,
      "srisk_usd_bn": 0.0,
      "market_cap_usd_bn": 895.331984,
      "debt_usd_bn": 4536.437,
      "srisk_share_pct": 0.0,
      "bank_id": "JPM"
    },
    {
      "bank_name": "Mizuho Financial Group",
      "region": "JP",
      "covar_index": "^N225",
      "mes": -0.031346,
      "lrmes": 0.397213,
      "covar": -0.03237,
      "delta_covar": -0.015941,
      "covar_beta": 0.387937,
      "srisk_usd_bn": 78.60877,
      "market_cap_usd_bn": 117.923804,
      "debt_usd_bn": 1800.062777,
      "srisk_share_pct": 2.3991,
      "bank_id": "MFG"
    },
    {
      "bank_name": "Morgan Stanley",
      "region": "US",
      "covar_index": "^GSPC",
      "mes": -0.02277,
      "lrmes": 0.496154,
      "covar": -0.016687,
      "delta_covar": -0.008031,
      "covar_beta": 0.294558,
      "srisk_usd_bn": 0.0,
      "market_cap_usd_bn": 356.513685,
      "debt_usd_bn": 1466.034,
      "srisk_share_pct": 0.0,
      "bank_id": "MS"
    },
    {
      "bank_name": "Mitsubishi UFJ Financial",
      "region": "JP",
      "covar_index": "^N225",
      "mes": -0.020326,
      "lrmes": 0.296708,
      "covar": -0.031972,
      "delta_covar": -0.013145,
      "covar_beta": 0.407924,
      "srisk_usd_bn": 54.474522,
      "market_cap_usd_bn": 228.022166,
      "debt_usd_bn": 2525.143184,
      "srisk_share_pct": 1.6625,
      "bank_id": "MUFG"
    },
    {
      "bank_name": "Banco Santander",
      "region": "EU",
      "covar_index": "^STOXX50E",
      "mes": -0.023837,
      "lrmes": 0.540748,
      "covar": -0.018544,
      "delta_covar": -0.010584,
      "covar_beta": 0.373535,
      "srisk_usd_bn": 76.909812,
      "market_cap_usd_bn": 195.328625,
      "debt_usd_bn": 1992.980414,
      "srisk_share_pct": 2.3473,
      "bank_id": "SAN"
    },
    {
      "bank_name": "Sumitomo Mitsui Financial",
      "region": "JP",
      "covar_index": "^N225",
      "mes": -0.023988,
      "lrmes": 0.321868,
      "covar": -0.031377,
      "delta_covar": -0.013218,
      "covar_beta": 0.406534,
      "srisk_usd_bn": 59.711492,
      "market_cap_usd_bn": 152.366778,
      "debt_usd_bn": 1934.628918,
      "srisk_share_pct": 1.8224,
      "bank_id": "SMFG"
    },
    {
      "bank_name": "Standard Chartered",
      "region": "GB",
      "covar_index": "^FTSE",
      "mes": -0.02922,
      "lrmes": 0.61326,
      "covar": -0.015765,
      "delta_covar": -0.007673,
      "covar_beta": 0.251177,
      "srisk_usd_bn": 43.355876,
      "market_cap_usd_bn": 33.996292,
      "debt_usd_bn": 693.147434,
      "srisk_share_pct": 1.3232,
      "bank_id": "STAN"
    },
    {
      "bank_name": "State Street",
      "region": "US",
      "covar_index": "^GSPC",
      "mes": -0.018756,
      "lrmes": 0.435789,
      "covar": -0.018865,
      "delta_covar": -0.008134,
      "covar_beta": 0.285315,
      "srisk_usd_bn": 4.318942,
      "market_cap_usd_bn": 47.844589,
      "debt_usd_bn": 364.423,
      "srisk_share_pct": 0.1318,
      "bank_id": "STT"
    },
    {
      "bank_name": "UBS Group",
      "region": "EU",
      "covar_index": "^STOXX50E",
      "mes": -0.014436,
      "lrmes": 0.369557,
      "covar": -0.019569,
      "delta_covar": -0.007664,
      "covar_beta": 0.335509,
      "srisk_usd_bn": 40.280178,
      "market_cap_usd_bn": 108.376511,
      "debt_usd_bn": 1289.242539,
      "srisk_share_pct": 1.2293,
      "bank_id": "UBS"
    },
    {
      "bank_name": "UniCredit",
      "region": "EU",
      "covar_index": "^STOXX50E",
      "mes": -0.020605,
      "lrmes": 0.533051,
      "covar": -0.021952,
      "delta_covar": -0.010867,
      "covar_beta": 0.365919,
      "srisk_usd_bn": 18.166365,
      "market_cap_usd_bn": 135.05059,
      "debt_usd_bn": 952.289476,
      "srisk_share_pct": 0.5544,
      "bank_id": "UCG"
    },
    {
      "bank_name": "Wells Fargo",
      "region": "US",
      "covar_index": "^GSPC",
      "mes": -0.01507,
      "lrmes": 0.347402,
      "covar": -0.018187,
      "delta_covar": -0.007493,
      "covar_beta": 0.241915,
      "srisk_usd_bn": 7.462385,
      "market_cap_usd_bn": 257.453734,
      "debt_usd_bn": 2025.439,
      "srisk_share_pct": 0.2277,
      "bank_id": "WFC"
    }
  ]
}