{
  "date": "2026-03-03",
  "generated_at": "2026-04-10T22:36:53.376465+00:00",
  "methodology_version": "1.0",
  "parameters": {
    "srisk_k": 0.08,
    "covar_quantile": 0.05,
    "covar_window_days": 252,
    "lrmes_horizon_days": 22,
    "lrmes_market_drop": 0.4,
    "mes_tail_pct": 0.05
  },
  "system_srisk_usd_bn": 496.8348,
  "bank_count": 11,
  "banks": [
    {
      "bank_name": "Bank of America",
      "region": "US",
      "covar_index": "^GSPC",
      "mes": -0.035373,
      "lrmes": 0.481866,
      "covar": -0.027192,
      "delta_covar": -0.015126,
      "covar_beta": 0.473439,
      "srisk_usd_bn": 78.692973,
      "market_cap_usd_bn": 356.602894,
      "debt_usd_bn": 3108.495,
      "srisk_share_pct": 15.8389,
      "bank_id": "BAC"
    },
    {
      "bank_name": "Barclays",
      "region": "GB",
      "covar_index": "^FTSE",
      "mes": -0.040208,
      "lrmes": 0.672151,
      "covar": -0.016861,
      "delta_covar": -0.010674,
      "covar_beta": 0.294047,
      "srisk_usd_bn": 74.431219,
      "market_cap_usd_bn": 43.159755,
      "debt_usd_bn": 1093.113899,
      "srisk_share_pct": 14.9811,
      "bank_id": "BARC"
    },
    {
      "bank_name": "Bank of New York Mellon",
      "region": "US",
      "covar_index": "^GSPC",
      "mes": -0.026779,
      "lrmes": 0.392127,
      "covar": -0.027199,
      "delta_covar": -0.015523,
      "covar_beta": 0.621446,
      "srisk_usd_bn": 0.0,
      "market_cap_usd_bn": 82.252327,
      "debt_usd_bn": 427.492,
      "srisk_share_pct": 0.0,
      "bank_id": "BK"
    },
    {
      "bank_name": "Citigroup",
      "region": "US",
      "covar_index": "^GSPC",
      "mes": -0.04238,
      "lrmes": 0.545148,
      "covar": -0.028207,
      "delta_covar": -0.0176,
      "covar_beta": 0.457058,
      "srisk_usd_bn": 114.391086,
      "market_cap_usd_bn": 193.754577,
      "debt_usd_bn": 2443.38,
      "srisk_share_pct": 23.024,
      "bank_id": "C"
    },
    {
      "bank_name": "Goldman Sachs",
      "region": "US",
      "covar_index": "^GSPC",
      "mes": -0.040017,
      "lrmes": 0.524721,
      "covar": -0.024116,
      "delta_covar": -0.014154,
      "covar_beta": 0.469691,
      "srisk_usd_bn": 22.821803,
      "market_cap_usd_bn": 255.973141,
      "debt_usd_bn": 1684.348,
      "srisk_share_pct": 4.5934,
      "bank_id": "GS"
    },
    {
      "bank_name": "HSBC Holdings",
      "region": "GB",
      "covar_index": "^FTSE",
      "mes": -0.031288,
      "lrmes": 0.580123,
      "covar": -0.012244,
      "delta_covar": -0.006648,
      "covar_beta": 0.240743,
      "srisk_usd_bn": 118.242231,
      "market_cap_usd_bn": 161.417944,
      "debt_usd_bn": 2257.447693,
      "srisk_share_pct": 23.7991,
      "bank_id": "HSBC"
    },
    {
      "bank_name": "JPMorgan Chase",
      "region": "US",
      "covar_index": "^GSPC",
      "mes": -0.031383,
      "lrmes": 0.441983,
      "covar": -0.028609,
      "delta_covar": -0.016548,
      "covar_beta": 0.625692,
      "srisk_usd_bn": 0.0,
      "market_cap_usd_bn": 805.687639,
      "debt_usd_bn": 4062.462,
      "srisk_share_pct": 0.0,
      "bank_id": "JPM"
    },
    {
      "bank_name": "Morgan Stanley",
      "region": "US",
      "covar_index": "^GSPC",
      "mes": -0.043143,
      "lrmes": 0.551549,
      "covar": -0.025559,
      "delta_covar": -0.016192,
      "covar_beta": 0.512052,
      "srisk_usd_bn": 0.0,
      "market_cap_usd_bn": 263.505396,
      "debt_usd_bn": 1307.618,
      "srisk_share_pct": 0.0,
      "bank_id": "MS"
    },
    {
      "bank_name": "Standard Chartered",
      "region": "GB",
      "covar_index": "^FTSE",
      "mes": -0.034968,
      "lrmes": 0.620866,
      "covar": -0.013206,
      "delta_covar": -0.006121,
      "covar_beta": 0.22593,
      "srisk_usd_bn": 41.946785,
      "market_cap_usd_bn": 27.741352,
      "debt_usd_bn": 645.288334,
      "srisk_share_pct": 8.4428,
      "bank_id": "STAN"
    },
    {
      "bank_name": "State Street",
      "region": "US",
      "covar_index": "^GSPC",
      "mes": -0.03615,
      "lrmes": 0.489301,
      "covar": -0.028301,
      "delta_covar": -0.018617,
      "covar_beta": 0.575943,
      "srisk_usd_bn": 10.676927,
      "market_cap_usd_bn": 34.861741,
      "debt_usd_bn": 338.206,
      "srisk_share_pct": 2.149,
      "bank_id": "STT"
    },
    {
      "bank_name": "Wells Fargo",
      "region": "US",
      "covar_index": "^GSPC",
      "mes": -0.035273,
      "lrmes": 0.480907,
      "covar": -0.026417,
      "delta_covar": -0.01529,
      "covar_beta": 0.452737,
      "srisk_usd_bn": 35.631784,
      "market_cap_usd_bn": 254.657506,
      "debt_usd_bn": 1965.593,
      "srisk_share_pct": 7.1718,
      "bank_id": "WFC"
    }
  ]
}